gp_core-6.0.1.dist-info/METADATA
gp_core-6.0.1.dist-info/WHEEL
gp_core-6.0.1.dist-info/licenses/LICENSE
gp_core/py.typed
gp_core/models.pyi
gp_core/algorithms.pyi
gp_core/literal_matchers.pyi
gp_core/__init__.py
gp_core/gp_core.cpython-310-x86_64-linux-gnu.so
gp_core-6.0.1.dist-info/RECORD
