Metadata-Version: 2.4
Name: gp_core
Version: 6.0.1
Classifier: Programming Language :: Rust
Classifier: Programming Language :: Python :: Implementation :: CPython
License-File: LICENSE
Summary: A library to build semantic descriptions of tables
Author-email: Binh Vu <bvu687@gmail.com>
Requires-Python: >=3.10
Project-URL: homepage, https://github.com/binh-vu/gp
Project-URL: repository, https://github.com/binh-vu/gp
